skylynx/__init__.py
skylynx/text.py
skylynx/utils.py
skylynx-0.1.3.dist-info/LICENSE
skylynx-0.1.3.dist-info/METADATA
skylynx-0.1.3.dist-info/WHEEL
skylynx-0.1.3.dist-info/top_level.txt
skylynx-0.1.3.dist-info/RECORD
