Metadata-Version: 2.1
Name: skylynx
Version: 0.1.3
Summary: Python support functions package
Home-page: https://github.com/basameera/skylynx
Author: Sameera Sandaruwan
Author-email: basameera@protonmail.com
License: MIT
Platform: UNKNOWN
Classifier: License :: OSI Approved :: MIT License
Classifier: Programming Language :: Python :: 3
Classifier: Programming Language :: Python :: 3.6
Classifier: Programming Language :: Python :: 3.7
Classifier: Programming Language :: Python :: 3.8
Requires-Python: >=3.6
Requires-Dist: blessings (>=1.7)
Requires-Dist: PyYAML (>=5.1)
